/*******************************************************************************
 * Copyright (c) 2005-2007 UAB "MAKSINETA".
 * All rights reserved. This program and the accompanying materials
 * are made available under the terms of the Common Public License Version 1.0
 * which accompanies this distribution, and is available at
 * http://www.eclipse.org/legal/cpl-v10.html
 *
 * Contributors:
 *     "Maxim Kizub" mkizub@symade.com - initial design and implementation
 *******************************************************************************/
package kiev.be.java15;
import syntax kiev.Syntax;

/**
 * @author Maxim Kizub
 * @version $Revision$
 *
 */

public class OpCodeRules extends JConstants {

	public final JType[][] op_input_types;
	public final JType[][] op_output_types;
	
	
	public OpCodeRules(JTypeEnv jtenv) {
		
		// opcode input types (stack)
		this.op_input_types = new JType[][] {
			{/* no args */},			// opc_nop = 0;
			{/* no args */},			// opc_aconst_null = 1;
			{/* no args */},			// opc_iconst_m1 = 2;
			{/* no args */},			// opc_iconst_0 = 3;
			{/* no args */},			// opc_iconst_1 = 4;
			{/* no args */},			// opc_iconst_2 = 5;
			{/* no args */},			// opc_iconst_3 = 6;
			{/* no args */},			// opc_iconst_4 = 7;
			{/* no args */},			// opc_iconst_5 = 8;
			{/* no args */},			// opc_lconst_0 = 9;
			{/* no args */},			// opc_lconst_1 = 10;
			{/* no args */},			// opc_fconst_0 = 11;
			{/* no args */},			// opc_fconst_1 = 12;
			{/* no args */},			// opc_fconst_2 = 13;
			{/* no args */},			// opc_dconst_0 = 14;
			{/* no args */},			// opc_dconst_1 = 15;
			{/* no args */},			// opc_bipush = 16;
			{/* no args */},			// opc_sipush = 17;
			{/* no args */},			// opc_ldc = 18;
			{/* no args */},			// opc_ldc_w = 19;
			{/* no args */},			// opc_ldc2_w = 20;
			{/* no args */},			// opc_iload = 21;
			{/* no args */},			// opc_lload = 22;
			{/* no args */},			// opc_fload = 23;
			{/* no args */},			// opc_dload = 24;
			{/* no args */},			// opc_aload = 25;
			{/* no args */},			// opc_iload_0 = 26;
			{/* no args */},			// opc_iload_1 = 27;
			{/* no args */},			// opc_iload_2 = 28;
			{/* no args */},			// opc_iload_3 = 29;
			{/* no args */},			// opc_lload_0 = 30;
			{/* no args */},			// opc_lload_1 = 31;
			{/* no args */},			// opc_lload_2 = 32;
			{/* no args */},			// opc_lload_3 = 33;
			{/* no args */},			// opc_fload_0 = 34;
			{/* no args */},			// opc_fload_1 = 35;
			{/* no args */},			// opc_fload_2 = 36;
			{/* no args */},			// opc_fload_3 = 37;
			{/* no args */},			// opc_dload_0 = 38;
			{/* no args */},			// opc_dload_1 = 39;
			{/* no args */},			// opc_dload_2 = 40;
			{/* no args */},			// opc_dload_3 = 41;
			{/* no args */},			// opc_aload_0 = 42;
			{/* no args */},			// opc_aload_1 = 43;
			{/* no args */},			// opc_aload_2 = 44;
			{/* no args */},			// opc_aload_3 = 45;
			{jtenv.tpArray,	jtenv.tpInt},			// opc_iaload = 46;
			{jtenv.tpArray,	jtenv.tpInt},			// opc_laload = 47;
			{jtenv.tpArray,	jtenv.tpInt},			// opc_faload = 48;
			{jtenv.tpArray,	jtenv.tpInt},			// opc_daload = 49;
			{jtenv.tpArray,	jtenv.tpInt},			// opc_aaload = 50;
			{jtenv.tpArray,	jtenv.tpInt},			// opc_baload = 51;
			{jtenv.tpArray,	jtenv.tpInt},			// opc_caload = 52;
			{jtenv.tpArray,	jtenv.tpInt},			// opc_saload = 53;
			{jtenv.tpInt},					// opc_istore = 54;
			{jtenv.tpLong},					// opc_lstore = 55;
			{jtenv.tpFloat},					// opc_fstore = 56;
			{jtenv.tpDouble},					// opc_dstore = 57;
			{jtenv.tpObject},					// opc_astore = 58;
			{jtenv.tpInt},					// opc_istore_0 = 59;
			{jtenv.tpInt},					// opc_istore_1 = 60;
			{jtenv.tpInt},					// opc_istore_2 = 61;
			{jtenv.tpInt},					// opc_istore_3 = 62;
			{jtenv.tpLong},					// opc_lstore_0 = 63;
			{jtenv.tpLong},					// opc_lstore_1 = 64;
			{jtenv.tpLong},					// opc_lstore_2 = 65;
			{jtenv.tpLong},					// opc_lstore_3 = 66;
			{jtenv.tpFloat},					// opc_fstore_0 = 67;
			{jtenv.tpFloat},					// opc_fstore_1 = 68;
			{jtenv.tpFloat},					// opc_fstore_2 = 69;
			{jtenv.tpFloat},					// opc_fstore_3 = 70;
			{jtenv.tpDouble},					// opc_dstore_0 = 71;
			{jtenv.tpDouble},					// opc_dstore_1 = 72;
			{jtenv.tpDouble},					// opc_dstore_2 = 73;
			{jtenv.tpDouble},					// opc_dstore_3 = 74;
			{jtenv.tpObject},					// opc_astore_0 = 75;
			{jtenv.tpObject},					// opc_astore_1 = 76;
			{jtenv.tpObject},					// opc_astore_2 = 77;
			{jtenv.tpObject},					// opc_astore_3 = 78;
			{jtenv.tpArray,jtenv.tpInt,jtenv.tpInt},		// opc_iastore = 79;
			{jtenv.tpArray,jtenv.tpInt,jtenv.tpLong},		// opc_lastore = 80;
			{jtenv.tpArray,jtenv.tpInt,jtenv.tpFloat},	// opc_fastore = 81;
			{jtenv.tpArray,jtenv.tpInt,jtenv.tpDouble},	// opc_dastore = 82;
			{/* special */},	// opc_aastore = 83;
			{jtenv.tpArray,jtenv.tpInt,jtenv.tpByte},		// opc_bastore = 84;
			{jtenv.tpArray,jtenv.tpInt,jtenv.tpChar},		// opc_castore = 85;
			{jtenv.tpArray,jtenv.tpInt,jtenv.tpShort},	// opc_sastore = 86;
			{/* special */},			// opc_pop = 87;
			{/* special */},			// opc_pop2 = 88;
			{/* special */},			// opc_dup = 89;
			{/* special */},			// opc_dup_x1 = 90;
			{/* special */},			// opc_dup_x2 = 91;
			{/* special */},			// opc_dup2 = 92;
			{/* special */},			// opc_dup2_x1 = 93;
			{/* special */},			// opc_dup2_x2 = 94;
			{/* special */},			// opc_swap = 95;
			{jtenv.tpInt,		jtenv.tpInt},				// opc_iadd = 96;
			{jtenv.tpLong,		jtenv.tpLong},		// opc_ladd = 97;
			{jtenv.tpFloat,		jtenv.tpFloat},		// opc_fadd = 98;
			{jtenv.tpDouble,	jtenv.tpDouble},		// opc_dadd = 99;
			{jtenv.tpInt,		jtenv.tpInt},				// opc_isub = 100;
			{jtenv.tpLong,		jtenv.tpLong},		// opc_lsub = 101;
			{jtenv.tpFloat,		jtenv.tpFloat},		// opc_fsub = 102;
			{jtenv.tpDouble,	jtenv.tpDouble},		// opc_dsub = 103;
			{jtenv.tpInt,		jtenv.tpInt},				// opc_imul = 104;
			{jtenv.tpLong,		jtenv.tpLong},		// opc_lmul = 105;
			{jtenv.tpFloat,		jtenv.tpFloat},		// opc_fmul = 106;
			{jtenv.tpDouble,	jtenv.tpDouble},		// opc_dmul = 107;
			{jtenv.tpInt,		jtenv.tpInt},				// opc_idiv = 108;
			{jtenv.tpLong,		jtenv.tpLong},		// opc_ldiv = 109;
			{jtenv.tpFloat,		jtenv.tpFloat},		// opc_fdiv = 110;
			{jtenv.tpDouble,	jtenv.tpDouble},		// opc_ddiv = 111;
			{jtenv.tpInt,		jtenv.tpInt},				// opc_irem = 112;
			{jtenv.tpLong,		jtenv.tpLong},		// opc_lrem = 113;
			{jtenv.tpFloat,		jtenv.tpFloat},		// opc_frem = 114;
			{jtenv.tpDouble,	jtenv.tpDouble},		// opc_drem = 115;
			{jtenv.tpInt},					// opc_ineg = 116;
			{jtenv.tpLong},					// opc_lneg = 117;
			{jtenv.tpFloat},					// opc_fneg = 118;
			{jtenv.tpDouble},					// opc_dneg = 119;
			{jtenv.tpInt,		jtenv.tpInt},				// opc_ishl = 120;
			{jtenv.tpLong,		jtenv.tpInt},			// opc_lshl = 121;
			{jtenv.tpInt,		jtenv.tpInt},				// opc_ishr = 122;
			{jtenv.tpLong,		jtenv.tpInt},			// opc_lshr = 123;
			{jtenv.tpInt,		jtenv.tpInt},				// opc_iushr = 124;
			{jtenv.tpLong,		jtenv.tpInt},			// opc_lushr = 125;
			{jtenv.tpInt,		jtenv.tpInt},				// opc_iand = 126;
			{jtenv.tpLong,		jtenv.tpLong},		// opc_land = 127;
			{jtenv.tpInt,		jtenv.tpInt},				// opc_ior = 128;
			{jtenv.tpLong,		jtenv.tpLong},		// opc_lor = 129;
			{jtenv.tpInt,		jtenv.tpInt},				// opc_ixor = 130;
			{jtenv.tpLong,		jtenv.tpLong},		// opc_lxor = 131;
			{},								// opc_iinc = 132;
			{jtenv.tpInt},					// opc_i2l = 133;
			{jtenv.tpInt},					// opc_i2f = 134;
			{jtenv.tpInt},					// opc_i2d = 135;
			{jtenv.tpLong},					// opc_l2i = 136;
			{jtenv.tpLong},					// opc_l2f = 137;
			{jtenv.tpLong},					// opc_l2d = 138;
			{jtenv.tpFloat},					// opc_f2i = 139;
			{jtenv.tpFloat},					// opc_f2l = 140;
			{jtenv.tpFloat},					// opc_f2d = 141;
			{jtenv.tpDouble},					// opc_d2i = 142;
			{jtenv.tpDouble},					// opc_d2l = 143;
			{jtenv.tpDouble},					// opc_d2f = 144;
			{jtenv.tpInt},					// opc_i2b = 145;
			{jtenv.tpInt},					// opc_i2c = 146;
			{jtenv.tpInt},					// opc_i2s = 147;
			{jtenv.tpLong,		jtenv.tpLong},		// opc_lcmp = 148;
			{jtenv.tpFloat,		jtenv.tpFloat},		// opc_fcmpl = 149;
			{jtenv.tpFloat,		jtenv.tpFloat},		// opc_fcmpg = 150;
			{jtenv.tpDouble,	jtenv.tpDouble},		// opc_dcmpl = 151;
			{jtenv.tpDouble,	jtenv.tpDouble},		// opc_dcmpg = 152;
			{jtenv.tpInt},					// opc_ifeq = 153;
			{jtenv.tpInt},					// opc_ifne = 154;
			{jtenv.tpInt},					// opc_iflt = 155;
			{jtenv.tpInt},					// opc_ifge = 156;
			{jtenv.tpInt},					// opc_ifgt = 157;
			{jtenv.tpInt},					// opc_ifle = 158;
			{jtenv.tpInt,		jtenv.tpInt},				// opc_if_icmpeq = 159;
			{jtenv.tpInt,		jtenv.tpInt},				// opc_if_icmpne = 160;
			{jtenv.tpInt,		jtenv.tpInt},				// opc_if_icmplt = 161;
			{jtenv.tpInt,		jtenv.tpInt},				// opc_if_icmpge = 162;
			{jtenv.tpInt,		jtenv.tpInt},				// opc_if_icmpgt = 163;
			{jtenv.tpInt,		jtenv.tpInt},				// opc_if_icmple = 164;
			{jtenv.tpObject,	jtenv.tpObject},		// opc_if_acmpeq = 165;
			{jtenv.tpObject,	jtenv.tpObject},		// opc_if_acmpne = 166;
			{/* no args */},			// opc_goto = 167;
			{/* no args */},			// opc_jsr = 168;
			{/* no args */},			// opc_ret = 169;
			{jtenv.tpInt},					// opc_tableswitch = 170;
			{jtenv.tpInt},					// opc_lookupswitch = 171;
			{jtenv.tpInt},					// opc_ireturn = 172;
			{jtenv.tpLong},					// opc_lreturn = 173;
			{jtenv.tpFloat},					// opc_freturn = 174;
			{jtenv.tpDouble},					// opc_dreturn = 175;
			{jtenv.tpObject},					// opc_areturn = 176;
			{/* no args */},			// opc_return = 177;
			{/* special */},			// opc_getstatic = 178;
			{/* special */},			// opc_putstatic = 179;
			{/* special */},			// opc_getfield = 180;
			{/* special */},			// opc_putfield = 181;
			{/* special */},			// opc_invokevirtual = 182;
			{/* special */},			// opc_invokespecial = 183;
			{/* special */},			// opc_invokestatic = 184;
			{/* special */},			// opc_invokeinterface = 185;
			{/* undefined */},			// opc_xxxunusedxxx = 186;
			{/* no args */},			// opc_new = 187;
			{jtenv.tpInt},					// opc_newarray = 188;
			{jtenv.tpInt},					// opc_anewarray = 189;
			{jtenv.tpArray},					// opc_arraylength = 190;
			{jtenv.tpObject},					// opc_athrow = 191;
			{jtenv.tpObject},					// opc_checkcast = 192;
			{jtenv.tpObject},					// opc_instanceof = 193;
			{jtenv.tpObject},					// opc_monitorenter = 194;
			{jtenv.tpObject},					// opc_monitorexit = 195;
			{/* special */},			// opc_wide = 196;
			{/* special */},			// opc_multianewarray = 197;
			{jtenv.tpObject},					// opc_ifnull = 198;
			{jtenv.tpObject},					// opc_ifnonnull = 199;
			{/* no args */},			// opc_goto_w = 200;
			{/* no args */},			// opc_jsr_w = 201;
			{/* no args */},			// opc_breakpoint = 202;
	
			{/* special */},			// opc_newmethodref = 203;
			{/* special */},			// opc_addargs = 204;
			{/* special */},			// opc_invokemethodref = 205;
		};

		// opcode ouType.tput types (stack)
		this.op_output_types = new JType[][] {
			{/* no rets */},			// opc_nop = 0;
			{jtenv.tpObject},				// opc_aconst_null = 1;
			{jtenv.tpByte},					// opc_iconst_m1 = 2;
			{jtenv.tpByte},					// opc_iconst_0 = 3;
			{jtenv.tpByte},					// opc_iconst_1 = 4;
			{jtenv.tpByte},					// opc_iconst_2 = 5;
			{jtenv.tpByte},					// opc_iconst_3 = 6;
			{jtenv.tpByte},					// opc_iconst_4 = 7;
			{jtenv.tpByte},					// opc_iconst_5 = 8;
			{jtenv.tpLong},					// opc_lconst_0 = 9;
			{jtenv.tpLong},					// opc_lconst_1 = 10;
			{jtenv.tpFloat},					// opc_fconst_0 = 11;
			{jtenv.tpFloat},					// opc_fconst_1 = 12;
			{jtenv.tpFloat},					// opc_fconst_2 = 13;
			{jtenv.tpDouble},				// opc_dconst_0 = 14;
			{jtenv.tpDouble},				// opc_dconst_1 = 15;
			{jtenv.tpByte},					// opc_bipush = 16;
			{jtenv.tpShort},					// opc_sipush = 17;
			{/* special */},			// opc_ldc = 18;
			{/* special */},			// opc_ldc_w = 19;
			{/* special */},			// opc_ldc2_w = 20;
			{jtenv.tpInt},					// opc_iload = 21;
			{jtenv.tpLong},					// opc_lload = 22;
			{jtenv.tpFloat},					// opc_fload = 23;
			{jtenv.tpDouble},				// opc_dload = 24;
			{jtenv.tpObject},				// opc_aload = 25;
			{jtenv.tpInt},					// opc_iload_0 = 26;
			{jtenv.tpInt},					// opc_iload_1 = 27;
			{jtenv.tpInt},					// opc_iload_2 = 28;
			{jtenv.tpInt},					// opc_iload_3 = 29;
			{jtenv.tpLong},					// opc_lload_0 = 30;
			{jtenv.tpLong},					// opc_lload_1 = 31;
			{jtenv.tpLong},					// opc_lload_2 = 32;
			{jtenv.tpLong},					// opc_lload_3 = 33;
			{jtenv.tpFloat},					// opc_fload_0 = 34;
			{jtenv.tpFloat},					// opc_fload_1 = 35;
			{jtenv.tpFloat},					// opc_fload_2 = 36;
			{jtenv.tpFloat},					// opc_fload_3 = 37;
			{jtenv.tpDouble},				// opc_dload_0 = 38;
			{jtenv.tpDouble},				// opc_dload_1 = 39;
			{jtenv.tpDouble},				// opc_dload_2 = 40;
			{jtenv.tpDouble},				// opc_dload_3 = 41;
			{jtenv.tpObject},				// opc_aload_0 = 42;
			{jtenv.tpObject},				// opc_aload_1 = 43;
			{jtenv.tpObject},				// opc_aload_2 = 44;
			{jtenv.tpObject},				// opc_aload_3 = 45;
			{jtenv.tpInt},					// opc_iaload = 46;
			{jtenv.tpLong},					// opc_laload = 47;
			{jtenv.tpFloat},					// opc_faload = 48;
			{jtenv.tpDouble},				// opc_daload = 49;
			{/* special */},				// opc_aaload = 50;
			{jtenv.tpByte},					// opc_baload = 51;
			{jtenv.tpChar},					// opc_caload = 52;
			{jtenv.tpShort},					// opc_saload = 53;
			{/* no rets */},			// opc_istore = 54;
			{/* no rets */},			// opc_lstore = 55;
			{/* no rets */},			// opc_fstore = 56;
			{/* no rets */},			// opc_dstore = 57;
			{/* no rets */},			// opc_astore = 58;
			{/* no rets */},			// opc_istore_0 = 59;
			{/* no rets */},			// opc_istore_1 = 60;
			{/* no rets */},			// opc_istore_2 = 61;
			{/* no rets */},			// opc_istore_3 = 62;
			{/* no rets */},			// opc_lstore_0 = 63;
			{/* no rets */},			// opc_lstore_1 = 64;
			{/* no rets */},			// opc_lstore_2 = 65;
			{/* no rets */},			// opc_lstore_3 = 66;
			{/* no rets */},			// opc_fstore_0 = 67;
			{/* no rets */},			// opc_fstore_1 = 68;
			{/* no rets */},			// opc_fstore_2 = 69;
			{/* no rets */},			// opc_fstore_3 = 70;
			{/* no rets */},			// opc_dstore_0 = 71;
			{/* no rets */},			// opc_dstore_1 = 72;
			{/* no rets */},			// opc_dstore_2 = 73;
			{/* no rets */},			// opc_dstore_3 = 74;
			{/* no rets */},			// opc_astore_0 = 75;
			{/* no rets */},			// opc_astore_1 = 76;
			{/* no rets */},			// opc_astore_2 = 77;
			{/* no rets */},			// opc_astore_3 = 78;
			{/* no rets */},			// opc_iastore = 79;
			{/* no rets */},			// opc_lastore = 80;
			{/* no rets */},			// opc_fastore = 81;
			{/* no rets */},			// opc_dastore = 82;
			{/* no rets */},			// opc_aastore = 83;
			{/* no rets */},			// opc_bastore = 84;
			{/* no rets */},			// opc_castore = 85;
			{/* no rets */},			// opc_sastore = 86;
			{/* no rets */},			// opc_pop = 87;
			{/* no rets */},			// opc_pop2 = 88;
			{/* special */},			// opc_dup = 89;
			{/* special */},			// opc_dup_x1 = 90;
			{/* special */},			// opc_dup_x2 = 91;
			{/* special */},			// opc_dup2 = 92;
			{/* special */},			// opc_dup2_x1 = 93;
			{/* special */},			// opc_dup2_x2 = 94;
			{/* special */},			// opc_swap = 95;
			{jtenv.tpInt},					// opc_iadd = 96;
			{jtenv.tpLong},					// opc_ladd = 97;
			{jtenv.tpFloat},					// opc_fadd = 98;
			{jtenv.tpDouble},				// opc_dadd = 99;
			{jtenv.tpInt},					// opc_isub = 100;
			{jtenv.tpLong},					// opc_lsub = 101;
			{jtenv.tpFloat},					// opc_fsub = 102;
			{jtenv.tpDouble},				// opc_dsub = 103;
			{jtenv.tpInt},					// opc_imul = 104;
			{jtenv.tpLong},					// opc_lmul = 105;
			{jtenv.tpFloat},					// opc_fmul = 106;
			{jtenv.tpDouble},				// opc_dmul = 107;
			{jtenv.tpInt},					// opc_idiv = 108;
			{jtenv.tpLong},					// opc_ldiv = 109;
			{jtenv.tpFloat},					// opc_fdiv = 110;
			{jtenv.tpDouble},				// opc_ddiv = 111;
			{jtenv.tpInt},					// opc_irem = 112;
			{jtenv.tpLong},					// opc_lrem = 113;
			{jtenv.tpFloat},					// opc_frem = 114;
			{jtenv.tpDouble},				// opc_drem = 115;
			{jtenv.tpInt},					// opc_ineg = 116;
			{jtenv.tpLong},					// opc_lneg = 117;
			{jtenv.tpFloat},					// opc_fneg = 118;
			{jtenv.tpDouble},				// opc_dneg = 119;
			{jtenv.tpInt},					// opc_ishl = 120;
			{jtenv.tpLong},					// opc_lshl = 121;
			{jtenv.tpInt},					// opc_ishr = 122;
			{jtenv.tpLong},					// opc_lshr = 123;
			{jtenv.tpInt},					// opc_iushr = 124;
			{jtenv.tpLong},					// opc_lushr = 125;
			{jtenv.tpInt},					// opc_iand = 126;
			{jtenv.tpLong},					// opc_land = 127;
			{jtenv.tpInt},					// opc_ior = 128;
			{jtenv.tpLong},					// opc_lor = 129;
			{jtenv.tpInt},					// opc_ixor = 130;
			{jtenv.tpLong},					// opc_lxor = 131;
			{},								// opc_iinc = 132;
			{jtenv.tpLong},					// opc_i2l = 133;
			{jtenv.tpFloat},					// opc_i2f = 134;
			{jtenv.tpDouble},				// opc_i2d = 135;
			{jtenv.tpInt},					// opc_l2i = 136;
			{jtenv.tpFloat},					// opc_l2f = 137;
			{jtenv.tpDouble},				// opc_l2d = 138;
			{jtenv.tpInt},					// opc_f2i = 139;
			{jtenv.tpLong},					// opc_f2l = 140;
			{jtenv.tpDouble},				// opc_f2d = 141;
			{jtenv.tpInt},					// opc_d2i = 142;
			{jtenv.tpLong},					// opc_d2l = 143;
			{jtenv.tpFloat},					// opc_d2f = 144;
			{jtenv.tpByte},					// opc_i2b = 145;
			{jtenv.tpChar},					// opc_i2c = 146;
			{jtenv.tpShort},					// opc_i2s = 147;
			{jtenv.tpInt},			// opc_lcmp = 148;
			{jtenv.tpInt},			// opc_fcmpl = 149;
			{jtenv.tpInt},			// opc_fcmpg = 150;
			{jtenv.tpInt},			// opc_dcmpl = 151;
			{jtenv.tpInt},			// opc_dcmpg = 152;
			{/* no rets */},			// opc_ifeq = 153;
			{/* no rets */},			// opc_ifne = 154;
			{/* no rets */},			// opc_iflt = 155;
			{/* no rets */},			// opc_ifge = 156;
			{/* no rets */},			// opc_ifgt = 157;
			{/* no rets */},			// opc_ifle = 158;
			{/* no rets */},			// opc_if_icmpeq = 159;
			{/* no rets */},			// opc_if_icmpne = 160;
			{/* no rets */},			// opc_if_icmplt = 161;
			{/* no rets */},			// opc_if_icmpge = 162;
			{/* no rets */},			// opc_if_icmpgt = 163;
			{/* no rets */},			// opc_if_icmple = 164;
			{/* no rets */},			// opc_if_acmpeq = 165;
			{/* no rets */},			// opc_if_acmpne = 166;
			{/* no rets */},			// opc_goto = 167;
			{/* no rets */},			// opc_jsr = 168;
			{/* no rets */},			// opc_ret = 169;
			{/* no rets */},			// opc_tableswitch = 170;
			{/* no rets */},			// opc_lookupswitch = 171;
			{/* no rets */},				// opc_ireturn = 172;
			{/* no rets */},				// opc_lreturn = 173;
			{/* no rets */},				// opc_freturn = 174;
			{/* no rets */},			// opc_dreturn = 175;
			{/* no rets */},			// opc_areturn = 176;
			{/* no rets */},			// opc_return = 177;
			{/* special */},			// opc_getstatic = 178;
			{/* special */},			// opc_putstatic = 179;
			{/* special */},			// opc_getfield = 180;
			{/* special */},			// opc_putfield = 181;
			{/* special */},			// opc_invokevirtual = 182;
			{/* special */},			// opc_invokespecial = 183;
			{/* special */},			// opc_invokestatic = 184;
			{/* special */},			// opc_invokeinterface = 185;
			{/* undefined */},			// opc_xxxunusedxxx = 186;
			{jtenv.tpObject},				// opc_new = 187;
			{jtenv.tpArray},					// opc_newarray = 188;
			{jtenv.tpArray},					// opc_anewarray = 189;
			{jtenv.tpInt},					// opc_arraylength = 190;
			{/* no rets */},			// opc_athrow = 191;
			{/* special */},			// opc_checkcast = 192;
			{jtenv.tpInt},					// opc_instanceof = 193;
			{/* no rets */},			// opc_monitorenter = 194;
			{/* no rets */},			// opc_monitorexit = 195;
			{/* special */},			// opc_wide = 196;
			{jtenv.tpArray},					// opc_multianewarray = 197;
			{/* no rets */},			// opc_ifnull = 198;
			{/* no rets */},			// opc_ifnonnull = 199;
			{/* no rets */},			// opc_goto_w = 200;
			{/* no rets */},			// opc_jsr_w = 201;
			{/* no rets */},			// opc_breakpoint = 202;
	
			{/* special */},			// opc_newmethodref = 203;
			{/* special */},			// opc_addargs = 204;
			{/* special */},			// opc_invokemethodref = 205;
		};
	}

}
