/*******************************************************************************
 * Copyright (c) 2005-2007 UAB "MAKSINETA".
 * All rights reserved. This program and the accompanying materials
 * are made available under the terms of the Common Public License Version 1.0
 * which accompanies this distribution, and is available at
 * http://www.eclipse.org/legal/cpl-v10.html
 *
 * Contributors:
 *     "Maxim Kizub" mkizub@symade.com - initial design and implementation
 *******************************************************************************/
package kiev.be.java15;

import syntax kiev.Syntax;

/**
 * @author Maxim Kizub
 * @version $Revision$
 *
 */

public interface OpCodeRules extends JConstants {

    // opcode input types (stack)
    public static final JType[][] op_input_types = new JType[][] {
		{/* no args */},			// opc_nop = 0;
		{/* no args */},			// opc_aconst_null = 1;
		{/* no args */},			// opc_iconst_m1 = 2;
		{/* no args */},			// opc_iconst_0 = 3;
		{/* no args */},			// opc_iconst_1 = 4;
		{/* no args */},			// opc_iconst_2 = 5;
		{/* no args */},			// opc_iconst_3 = 6;
		{/* no args */},			// opc_iconst_4 = 7;
		{/* no args */},			// opc_iconst_5 = 8;
		{/* no args */},			// opc_lconst_0 = 9;
		{/* no args */},			// opc_lconst_1 = 10;
		{/* no args */},			// opc_fconst_0 = 11;
		{/* no args */},			// opc_fconst_1 = 12;
		{/* no args */},			// opc_fconst_2 = 13;
		{/* no args */},			// opc_dconst_0 = 14;
		{/* no args */},			// opc_dconst_1 = 15;
		{/* no args */},			// opc_bipush = 16;
		{/* no args */},			// opc_sipush = 17;
		{/* no args */},			// opc_ldc = 18;
		{/* no args */},			// opc_ldc_w = 19;
		{/* no args */},			// opc_ldc2_w = 20;
		{/* no args */},			// opc_iload = 21;
		{/* no args */},			// opc_lload = 22;
		{/* no args */},			// opc_fload = 23;
		{/* no args */},			// opc_dload = 24;
		{/* no args */},			// opc_aload = 25;
		{/* no args */},			// opc_iload_0 = 26;
		{/* no args */},			// opc_iload_1 = 27;
		{/* no args */},			// opc_iload_2 = 28;
		{/* no args */},			// opc_iload_3 = 29;
		{/* no args */},			// opc_lload_0 = 30;
		{/* no args */},			// opc_lload_1 = 31;
		{/* no args */},			// opc_lload_2 = 32;
		{/* no args */},			// opc_lload_3 = 33;
		{/* no args */},			// opc_fload_0 = 34;
		{/* no args */},			// opc_fload_1 = 35;
		{/* no args */},			// opc_fload_2 = 36;
		{/* no args */},			// opc_fload_3 = 37;
		{/* no args */},			// opc_dload_0 = 38;
		{/* no args */},			// opc_dload_1 = 39;
		{/* no args */},			// opc_dload_2 = 40;
		{/* no args */},			// opc_dload_3 = 41;
		{/* no args */},			// opc_aload_0 = 42;
		{/* no args */},			// opc_aload_1 = 43;
		{/* no args */},			// opc_aload_2 = 44;
		{/* no args */},			// opc_aload_3 = 45;
		{JType.tpArray,	JType.tpInt},			// opc_iaload = 46;
		{JType.tpArray,	JType.tpInt},			// opc_laload = 47;
		{JType.tpArray,	JType.tpInt},			// opc_faload = 48;
		{JType.tpArray,	JType.tpInt},			// opc_daload = 49;
		{JType.tpArray,	JType.tpInt},			// opc_aaload = 50;
		{JType.tpArray,	JType.tpInt},			// opc_baload = 51;
		{JType.tpArray,	JType.tpInt},			// opc_caload = 52;
		{JType.tpArray,	JType.tpInt},			// opc_saload = 53;
		{JType.tpInt},					// opc_istore = 54;
		{JType.tpLong},					// opc_lstore = 55;
		{JType.tpFloat},					// opc_fstore = 56;
		{JType.tpDouble},					// opc_dstore = 57;
		{JType.tpObject},					// opc_astore = 58;
		{JType.tpInt},					// opc_istore_0 = 59;
		{JType.tpInt},					// opc_istore_1 = 60;
		{JType.tpInt},					// opc_istore_2 = 61;
		{JType.tpInt},					// opc_istore_3 = 62;
		{JType.tpLong},					// opc_lstore_0 = 63;
		{JType.tpLong},					// opc_lstore_1 = 64;
		{JType.tpLong},					// opc_lstore_2 = 65;
		{JType.tpLong},					// opc_lstore_3 = 66;
		{JType.tpFloat},					// opc_fstore_0 = 67;
		{JType.tpFloat},					// opc_fstore_1 = 68;
		{JType.tpFloat},					// opc_fstore_2 = 69;
		{JType.tpFloat},					// opc_fstore_3 = 70;
		{JType.tpDouble},					// opc_dstore_0 = 71;
		{JType.tpDouble},					// opc_dstore_1 = 72;
		{JType.tpDouble},					// opc_dstore_2 = 73;
		{JType.tpDouble},					// opc_dstore_3 = 74;
		{JType.tpObject},					// opc_astore_0 = 75;
		{JType.tpObject},					// opc_astore_1 = 76;
		{JType.tpObject},					// opc_astore_2 = 77;
		{JType.tpObject},					// opc_astore_3 = 78;
		{JType.tpArray,JType.tpInt,JType.tpInt},		// opc_iastore = 79;
		{JType.tpArray,JType.tpInt,JType.tpLong},		// opc_lastore = 80;
		{JType.tpArray,JType.tpInt,JType.tpFloat},	// opc_fastore = 81;
		{JType.tpArray,JType.tpInt,JType.tpDouble},	// opc_dastore = 82;
		{/* special */},	// opc_aastore = 83;
		{JType.tpArray,JType.tpInt,JType.tpByte},		// opc_bastore = 84;
		{JType.tpArray,JType.tpInt,JType.tpChar},		// opc_castore = 85;
		{JType.tpArray,JType.tpInt,JType.tpShort},	// opc_sastore = 86;
		{/* special */},			// opc_pop = 87;
		{/* special */},			// opc_pop2 = 88;
		{/* special */},			// opc_dup = 89;
		{/* special */},			// opc_dup_x1 = 90;
		{/* special */},			// opc_dup_x2 = 91;
		{/* special */},			// opc_dup2 = 92;
		{/* special */},			// opc_dup2_x1 = 93;
		{/* special */},			// opc_dup2_x2 = 94;
		{/* special */},			// opc_swap = 95;
		{JType.tpInt,		JType.tpInt},				// opc_iadd = 96;
		{JType.tpLong,		JType.tpLong},		// opc_ladd = 97;
		{JType.tpFloat,		JType.tpFloat},		// opc_fadd = 98;
		{JType.tpDouble,	JType.tpDouble},		// opc_dadd = 99;
		{JType.tpInt,		JType.tpInt},				// opc_isub = 100;
		{JType.tpLong,		JType.tpLong},		// opc_lsub = 101;
		{JType.tpFloat,		JType.tpFloat},		// opc_fsub = 102;
		{JType.tpDouble,	JType.tpDouble},		// opc_dsub = 103;
		{JType.tpInt,		JType.tpInt},				// opc_imul = 104;
		{JType.tpLong,		JType.tpLong},		// opc_lmul = 105;
		{JType.tpFloat,		JType.tpFloat},		// opc_fmul = 106;
		{JType.tpDouble,	JType.tpDouble},		// opc_dmul = 107;
		{JType.tpInt,		JType.tpInt},				// opc_idiv = 108;
		{JType.tpLong,		JType.tpLong},		// opc_ldiv = 109;
		{JType.tpFloat,		JType.tpFloat},		// opc_fdiv = 110;
		{JType.tpDouble,	JType.tpDouble},		// opc_ddiv = 111;
		{JType.tpInt,		JType.tpInt},				// opc_irem = 112;
		{JType.tpLong,		JType.tpLong},		// opc_lrem = 113;
		{JType.tpFloat,		JType.tpFloat},		// opc_frem = 114;
		{JType.tpDouble,	JType.tpDouble},		// opc_drem = 115;
		{JType.tpInt},					// opc_ineg = 116;
		{JType.tpLong},					// opc_lneg = 117;
		{JType.tpFloat},					// opc_fneg = 118;
		{JType.tpDouble},					// opc_dneg = 119;
		{JType.tpInt,		JType.tpInt},				// opc_ishl = 120;
		{JType.tpLong,		JType.tpInt},			// opc_lshl = 121;
		{JType.tpInt,		JType.tpInt},				// opc_ishr = 122;
		{JType.tpLong,		JType.tpInt},			// opc_lshr = 123;
		{JType.tpInt,		JType.tpInt},				// opc_iushr = 124;
		{JType.tpLong,		JType.tpInt},			// opc_lushr = 125;
		{JType.tpInt,		JType.tpInt},				// opc_iand = 126;
		{JType.tpLong,		JType.tpLong},		// opc_land = 127;
		{JType.tpInt,		JType.tpInt},				// opc_ior = 128;
		{JType.tpLong,		JType.tpLong},		// opc_lor = 129;
		{JType.tpInt,		JType.tpInt},				// opc_ixor = 130;
		{JType.tpLong,		JType.tpLong},		// opc_lxor = 131;
		{},								// opc_iinc = 132;
		{JType.tpInt},					// opc_i2l = 133;
		{JType.tpInt},					// opc_i2f = 134;
		{JType.tpInt},					// opc_i2d = 135;
		{JType.tpLong},					// opc_l2i = 136;
		{JType.tpLong},					// opc_l2f = 137;
		{JType.tpLong},					// opc_l2d = 138;
		{JType.tpFloat},					// opc_f2i = 139;
		{JType.tpFloat},					// opc_f2l = 140;
		{JType.tpFloat},					// opc_f2d = 141;
		{JType.tpDouble},					// opc_d2i = 142;
		{JType.tpDouble},					// opc_d2l = 143;
		{JType.tpDouble},					// opc_d2f = 144;
		{JType.tpInt},					// opc_i2b = 145;
		{JType.tpInt},					// opc_i2c = 146;
		{JType.tpInt},					// opc_i2s = 147;
		{JType.tpLong,		JType.tpLong},		// opc_lcmp = 148;
		{JType.tpFloat,		JType.tpFloat},		// opc_fcmpl = 149;
		{JType.tpFloat,		JType.tpFloat},		// opc_fcmpg = 150;
		{JType.tpDouble,	JType.tpDouble},		// opc_dcmpl = 151;
		{JType.tpDouble,	JType.tpDouble},		// opc_dcmpg = 152;
		{JType.tpInt},					// opc_ifeq = 153;
		{JType.tpInt},					// opc_ifne = 154;
		{JType.tpInt},					// opc_iflt = 155;
		{JType.tpInt},					// opc_ifge = 156;
		{JType.tpInt},					// opc_ifgt = 157;
		{JType.tpInt},					// opc_ifle = 158;
		{JType.tpInt,		JType.tpInt},				// opc_if_icmpeq = 159;
		{JType.tpInt,		JType.tpInt},				// opc_if_icmpne = 160;
		{JType.tpInt,		JType.tpInt},				// opc_if_icmplt = 161;
		{JType.tpInt,		JType.tpInt},				// opc_if_icmpge = 162;
		{JType.tpInt,		JType.tpInt},				// opc_if_icmpgt = 163;
		{JType.tpInt,		JType.tpInt},				// opc_if_icmple = 164;
		{JType.tpObject,	JType.tpObject},		// opc_if_acmpeq = 165;
		{JType.tpObject,	JType.tpObject},		// opc_if_acmpne = 166;
		{/* no args */},			// opc_goto = 167;
		{/* no args */},			// opc_jsr = 168;
		{/* no args */},			// opc_ret = 169;
		{JType.tpInt},					// opc_tableswitch = 170;
		{JType.tpInt},					// opc_lookupswitch = 171;
		{JType.tpInt},					// opc_ireturn = 172;
		{JType.tpLong},					// opc_lreturn = 173;
		{JType.tpFloat},					// opc_freturn = 174;
		{JType.tpDouble},					// opc_dreturn = 175;
		{JType.tpObject},					// opc_areturn = 176;
		{/* no args */},			// opc_return = 177;
		{/* special */},			// opc_getstatic = 178;
		{/* special */},			// opc_putstatic = 179;
		{/* special */},			// opc_getfield = 180;
		{/* special */},			// opc_putfield = 181;
		{/* special */},			// opc_invokevirtual = 182;
		{/* special */},			// opc_invokespecial = 183;
		{/* special */},			// opc_invokestatic = 184;
		{/* special */},			// opc_invokeinterface = 185;
		{/* undefined */},			// opc_xxxunusedxxx = 186;
		{/* no args */},			// opc_new = 187;
		{JType.tpInt},					// opc_newarray = 188;
		{JType.tpInt},					// opc_anewarray = 189;
		{JType.tpArray},					// opc_arraylength = 190;
		{JType.tpObject},					// opc_athrow = 191;
		{JType.tpObject},					// opc_checkcast = 192;
		{JType.tpObject},					// opc_instanceof = 193;
		{JType.tpObject},					// opc_monitorenter = 194;
		{JType.tpObject},					// opc_monitorexit = 195;
		{/* special */},			// opc_wide = 196;
		{/* special */},			// opc_multianewarray = 197;
		{JType.tpObject},					// opc_ifnull = 198;
		{JType.tpObject},					// opc_ifnonnull = 199;
		{/* no args */},			// opc_goto_w = 200;
		{/* no args */},			// opc_jsr_w = 201;
		{/* no args */},			// opc_breakpoint = 202;

		{/* special */},			// opc_newmethodref = 203;
		{/* special */},			// opc_addargs = 204;
		{/* special */},			// opc_invokemethodref = 205;
    };


    // opcode ouType.tput types (stack)
    public static final JType[][] op_output_types = new JType[][] {
		{/* no rets */},			// opc_nop = 0;
		{JType.tpObject},				// opc_aconst_null = 1;
		{JType.tpByte},					// opc_iconst_m1 = 2;
		{JType.tpByte},					// opc_iconst_0 = 3;
		{JType.tpByte},					// opc_iconst_1 = 4;
		{JType.tpByte},					// opc_iconst_2 = 5;
		{JType.tpByte},					// opc_iconst_3 = 6;
		{JType.tpByte},					// opc_iconst_4 = 7;
		{JType.tpByte},					// opc_iconst_5 = 8;
		{JType.tpLong},					// opc_lconst_0 = 9;
		{JType.tpLong},					// opc_lconst_1 = 10;
		{JType.tpFloat},					// opc_fconst_0 = 11;
		{JType.tpFloat},					// opc_fconst_1 = 12;
		{JType.tpFloat},					// opc_fconst_2 = 13;
		{JType.tpDouble},				// opc_dconst_0 = 14;
		{JType.tpDouble},				// opc_dconst_1 = 15;
		{JType.tpByte},					// opc_bipush = 16;
		{JType.tpShort},					// opc_sipush = 17;
		{/* special */},			// opc_ldc = 18;
		{/* special */},			// opc_ldc_w = 19;
		{/* special */},			// opc_ldc2_w = 20;
		{JType.tpInt},					// opc_iload = 21;
		{JType.tpLong},					// opc_lload = 22;
		{JType.tpFloat},					// opc_fload = 23;
		{JType.tpDouble},				// opc_dload = 24;
		{JType.tpObject},				// opc_aload = 25;
		{JType.tpInt},					// opc_iload_0 = 26;
		{JType.tpInt},					// opc_iload_1 = 27;
		{JType.tpInt},					// opc_iload_2 = 28;
		{JType.tpInt},					// opc_iload_3 = 29;
		{JType.tpLong},					// opc_lload_0 = 30;
		{JType.tpLong},					// opc_lload_1 = 31;
		{JType.tpLong},					// opc_lload_2 = 32;
		{JType.tpLong},					// opc_lload_3 = 33;
		{JType.tpFloat},					// opc_fload_0 = 34;
		{JType.tpFloat},					// opc_fload_1 = 35;
		{JType.tpFloat},					// opc_fload_2 = 36;
		{JType.tpFloat},					// opc_fload_3 = 37;
		{JType.tpDouble},				// opc_dload_0 = 38;
		{JType.tpDouble},				// opc_dload_1 = 39;
		{JType.tpDouble},				// opc_dload_2 = 40;
		{JType.tpDouble},				// opc_dload_3 = 41;
		{JType.tpObject},				// opc_aload_0 = 42;
		{JType.tpObject},				// opc_aload_1 = 43;
		{JType.tpObject},				// opc_aload_2 = 44;
		{JType.tpObject},				// opc_aload_3 = 45;
		{JType.tpInt},					// opc_iaload = 46;
		{JType.tpLong},					// opc_laload = 47;
		{JType.tpFloat},					// opc_faload = 48;
		{JType.tpDouble},				// opc_daload = 49;
		{/* special */},				// opc_aaload = 50;
		{JType.tpByte},					// opc_baload = 51;
		{JType.tpChar},					// opc_caload = 52;
		{JType.tpShort},					// opc_saload = 53;
		{/* no rets */},			// opc_istore = 54;
		{/* no rets */},			// opc_lstore = 55;
		{/* no rets */},			// opc_fstore = 56;
		{/* no rets */},			// opc_dstore = 57;
		{/* no rets */},			// opc_astore = 58;
		{/* no rets */},			// opc_istore_0 = 59;
		{/* no rets */},			// opc_istore_1 = 60;
		{/* no rets */},			// opc_istore_2 = 61;
		{/* no rets */},			// opc_istore_3 = 62;
		{/* no rets */},			// opc_lstore_0 = 63;
		{/* no rets */},			// opc_lstore_1 = 64;
		{/* no rets */},			// opc_lstore_2 = 65;
		{/* no rets */},			// opc_lstore_3 = 66;
		{/* no rets */},			// opc_fstore_0 = 67;
		{/* no rets */},			// opc_fstore_1 = 68;
		{/* no rets */},			// opc_fstore_2 = 69;
		{/* no rets */},			// opc_fstore_3 = 70;
		{/* no rets */},			// opc_dstore_0 = 71;
		{/* no rets */},			// opc_dstore_1 = 72;
		{/* no rets */},			// opc_dstore_2 = 73;
		{/* no rets */},			// opc_dstore_3 = 74;
		{/* no rets */},			// opc_astore_0 = 75;
		{/* no rets */},			// opc_astore_1 = 76;
		{/* no rets */},			// opc_astore_2 = 77;
		{/* no rets */},			// opc_astore_3 = 78;
		{/* no rets */},			// opc_iastore = 79;
		{/* no rets */},			// opc_lastore = 80;
		{/* no rets */},			// opc_fastore = 81;
		{/* no rets */},			// opc_dastore = 82;
		{/* no rets */},			// opc_aastore = 83;
		{/* no rets */},			// opc_bastore = 84;
		{/* no rets */},			// opc_castore = 85;
		{/* no rets */},			// opc_sastore = 86;
		{/* no rets */},			// opc_pop = 87;
		{/* no rets */},			// opc_pop2 = 88;
		{/* special */},			// opc_dup = 89;
		{/* special */},			// opc_dup_x1 = 90;
		{/* special */},			// opc_dup_x2 = 91;
		{/* special */},			// opc_dup2 = 92;
		{/* special */},			// opc_dup2_x1 = 93;
		{/* special */},			// opc_dup2_x2 = 94;
		{/* special */},			// opc_swap = 95;
		{JType.tpInt},					// opc_iadd = 96;
		{JType.tpLong},					// opc_ladd = 97;
		{JType.tpFloat},					// opc_fadd = 98;
		{JType.tpDouble},				// opc_dadd = 99;
		{JType.tpInt},					// opc_isub = 100;
		{JType.tpLong},					// opc_lsub = 101;
		{JType.tpFloat},					// opc_fsub = 102;
		{JType.tpDouble},				// opc_dsub = 103;
		{JType.tpInt},					// opc_imul = 104;
		{JType.tpLong},					// opc_lmul = 105;
		{JType.tpFloat},					// opc_fmul = 106;
		{JType.tpDouble},				// opc_dmul = 107;
		{JType.tpInt},					// opc_idiv = 108;
		{JType.tpLong},					// opc_ldiv = 109;
		{JType.tpFloat},					// opc_fdiv = 110;
		{JType.tpDouble},				// opc_ddiv = 111;
		{JType.tpInt},					// opc_irem = 112;
		{JType.tpLong},					// opc_lrem = 113;
		{JType.tpFloat},					// opc_frem = 114;
		{JType.tpDouble},				// opc_drem = 115;
		{JType.tpInt},					// opc_ineg = 116;
		{JType.tpLong},					// opc_lneg = 117;
		{JType.tpFloat},					// opc_fneg = 118;
		{JType.tpDouble},				// opc_dneg = 119;
		{JType.tpInt},					// opc_ishl = 120;
		{JType.tpLong},					// opc_lshl = 121;
		{JType.tpInt},					// opc_ishr = 122;
		{JType.tpLong},					// opc_lshr = 123;
		{JType.tpInt},					// opc_iushr = 124;
		{JType.tpLong},					// opc_lushr = 125;
		{JType.tpInt},					// opc_iand = 126;
		{JType.tpLong},					// opc_land = 127;
		{JType.tpInt},					// opc_ior = 128;
		{JType.tpLong},					// opc_lor = 129;
		{JType.tpInt},					// opc_ixor = 130;
		{JType.tpLong},					// opc_lxor = 131;
		{},								// opc_iinc = 132;
		{JType.tpLong},					// opc_i2l = 133;
		{JType.tpFloat},					// opc_i2f = 134;
		{JType.tpDouble},				// opc_i2d = 135;
		{JType.tpInt},					// opc_l2i = 136;
		{JType.tpFloat},					// opc_l2f = 137;
		{JType.tpDouble},				// opc_l2d = 138;
		{JType.tpInt},					// opc_f2i = 139;
		{JType.tpLong},					// opc_f2l = 140;
		{JType.tpDouble},				// opc_f2d = 141;
		{JType.tpInt},					// opc_d2i = 142;
		{JType.tpLong},					// opc_d2l = 143;
		{JType.tpFloat},					// opc_d2f = 144;
		{JType.tpByte},					// opc_i2b = 145;
		{JType.tpChar},					// opc_i2c = 146;
		{JType.tpShort},					// opc_i2s = 147;
		{JType.tpInt},			// opc_lcmp = 148;
		{JType.tpInt},			// opc_fcmpl = 149;
		{JType.tpInt},			// opc_fcmpg = 150;
		{JType.tpInt},			// opc_dcmpl = 151;
		{JType.tpInt},			// opc_dcmpg = 152;
		{/* no rets */},			// opc_ifeq = 153;
		{/* no rets */},			// opc_ifne = 154;
		{/* no rets */},			// opc_iflt = 155;
		{/* no rets */},			// opc_ifge = 156;
		{/* no rets */},			// opc_ifgt = 157;
		{/* no rets */},			// opc_ifle = 158;
		{/* no rets */},			// opc_if_icmpeq = 159;
		{/* no rets */},			// opc_if_icmpne = 160;
		{/* no rets */},			// opc_if_icmplt = 161;
		{/* no rets */},			// opc_if_icmpge = 162;
		{/* no rets */},			// opc_if_icmpgt = 163;
		{/* no rets */},			// opc_if_icmple = 164;
		{/* no rets */},			// opc_if_acmpeq = 165;
		{/* no rets */},			// opc_if_acmpne = 166;
		{/* no rets */},			// opc_goto = 167;
		{/* no rets */},			// opc_jsr = 168;
		{/* no rets */},			// opc_ret = 169;
		{/* no rets */},			// opc_tableswitch = 170;
		{/* no rets */},			// opc_lookupswitch = 171;
		{/* no rets */},				// opc_ireturn = 172;
		{/* no rets */},				// opc_lreturn = 173;
		{/* no rets */},				// opc_freturn = 174;
		{/* no rets */},			// opc_dreturn = 175;
		{/* no rets */},			// opc_areturn = 176;
		{/* no rets */},			// opc_return = 177;
		{/* special */},			// opc_getstatic = 178;
		{/* special */},			// opc_putstatic = 179;
		{/* special */},			// opc_getfield = 180;
		{/* special */},			// opc_putfield = 181;
		{/* special */},			// opc_invokevirtual = 182;
		{/* special */},			// opc_invokespecial = 183;
		{/* special */},			// opc_invokestatic = 184;
		{/* special */},			// opc_invokeinterface = 185;
		{/* undefined */},			// opc_xxxunusedxxx = 186;
		{JType.tpObject},				// opc_new = 187;
		{JType.tpArray},					// opc_newarray = 188;
		{JType.tpArray},					// opc_anewarray = 189;
		{JType.tpInt},					// opc_arraylength = 190;
		{/* no rets */},			// opc_athrow = 191;
		{/* special */},			// opc_checkcast = 192;
		{JType.tpInt},					// opc_instanceof = 193;
		{/* no rets */},			// opc_monitorenter = 194;
		{/* no rets */},			// opc_monitorexit = 195;
		{/* special */},			// opc_wide = 196;
		{JType.tpArray},					// opc_multianewarray = 197;
		{/* no rets */},			// opc_ifnull = 198;
		{/* no rets */},			// opc_ifnonnull = 199;
		{/* no rets */},			// opc_goto_w = 200;
		{/* no rets */},			// opc_jsr_w = 201;
		{/* no rets */},			// opc_breakpoint = 202;

		{/* special */},			// opc_newmethodref = 203;
		{/* special */},			// opc_addargs = 204;
		{/* special */},			// opc_invokemethodref = 205;
    };

}
